[
    // Wrap with Abbreviation
    {
        "keys": ["shift+ctrl+g"],
        "command": "emmet_wrap_with_abbreviation",
        "context": [{"key": "setting.is_widget",  "operand": false }]
    },
    // Increment/Decrement Number
    {
        "keys": ["ctrl+up"],
        "command": "emmet_increment_number",
        "args": { "delta": 1 }
    },
    {
        "keys": ["ctrl+down"],
        "command": "emmet_increment_number",
        "args": { "delta": -1 }
    },
    // Rename Tag
    {
        "keys": ["shift+ctrl+'"],
        "command": "emmet_rename_tag"
    },
    // auto indent
    {
        "keys": ["alt+shift+f"], "command": "reindent",
        "args": 
        {
            "single_line": false
        }
    },

    // Select Next Item
    {
        "keys": ["shift+ctrl+."],
        "command": "emmet_select_item"
    },

    // Select Previous Item
    {
        "keys": ["shift+ctrl+,"],
        "command": "emmet_select_item",
        "args": { "previous": true }
    }
]